odoo/addons/hr_period/README.rst
odoo/addons/hr_period/__init__.py
odoo/addons/hr_period/__manifest__.py
odoo/addons/hr_period/i18n/hr_period.pot
odoo/addons/hr_period/i18n/it.po
odoo/addons/hr_period/i18n/pt_BR.po
odoo/addons/hr_period/readme/CONTRIBUTORS.rst
odoo/addons/hr_period/readme/DESCRIPTION.rst
odoo/addons/hr_period/static/description/icon.png
odoo/addons/hr_period/static/description/index.html
odoo14_addon_hr_period-14.0.1.0.1.dev14.dist-info/METADATA
odoo14_addon_hr_period-14.0.1.0.1.dev14.dist-info/WHEEL
odoo14_addon_hr_period-14.0.1.0.1.dev14.dist-info/top_level.txt
odoo14_addon_hr_period-14.0.1.0.1.dev14.dist-info/RECORD
